luganda-ocr/__init__.py
luganda-ocr/example.py
luganda-ocr/model.py
luganda-ocr/utils.py
luganda_ocr/__init__.py
luganda_ocr/example.py
luganda_ocr/model.py
luganda_ocr/utils.py
luganda_ocr/models/basepath.py
luganda_ocr/models/sentenceModel.h5
luganda_ocr-4.0.0.dist-info/METADATA
luganda_ocr-4.0.0.dist-info/WHEEL
luganda_ocr-4.0.0.dist-info/top_level.txt
luganda_ocr-4.0.0.dist-info/RECORD
