Metadata-Version: 2.1
Name: luganda-ocr
Version: 4.0.0
Summary: An OCR package for Luganda language
Author: LugandaOCR
Author-email: beijukab@gmail.com
License: MIT
Requires-Dist: tensorflow (==2.14.0)
Requires-Dist: numpy
Requires-Dist: pandas
